nested_dicts/__init__.py
nested_dicts/nested_dicts.py
nested_dicts-0.0.0.dist-info/METADATA
nested_dicts-0.0.0.dist-info/WHEEL
nested_dicts-0.0.0.dist-info/licenses/LICENSE
nested_dicts-0.0.0.dist-info/RECORD
