Metadata-Version: 2.1
Name: nested_dicts
Version: 0.0.0
Summary: Self-nesting list-keyed dicts, multiple-defaults dicts, and TOML-style Array of Tables lists/dicts. 
Project-URL: Homepage, https://github.com/JamesParrott/Nested_dicts
Project-URL: Bug Tracker, https://github.com/JamesParrott/Nested_dicts/issues
Author-email: James Parrott <james.parrott@proton.me>
License: MIT License
License-File: LICENSE
Classifier: License :: OSI Approved :: MIT License
Classifier: Operating System :: OS Independent
Classifier: Programming Language :: Python :: 3
Requires-Python: >=3.7
Provides-Extra: tests
Requires-Dist: pytest; extra == 'tests'
